dynamic_range_compression/__init__.py
dynamic_range_compression/compressor.py
dynamic_range_compression/compressorHelper/__init__.py
dynamic_range_compression/compressorHelper/definitions.py
dynamic_range_compression/compressorHelper/envelope.py
dynamic_range_compression/compressorHelper/gainReduction.py
dynamic_range_compression-1.0.0.dist-info/METADATA
dynamic_range_compression-1.0.0.dist-info/WHEEL
dynamic_range_compression-1.0.0.dist-info/top_level.txt
dynamic_range_compression-1.0.0.dist-info/RECORD
