Metadata-Version: 2.4
Name: dynamic_range_compression
Version: 1.0.0
Summary: Dynamic range compression in Python based on Audacity's and Daniel Rudrich's algorithm
Home-page: https://github.com/jjenkins2004/PythonDynamicRangeCompression
Author: Joshua Jenkins
Classifier: Programming Language :: Python :: 3
Classifier: License :: OSI Approved :: MIT License
Classifier: Operating System :: OS Independent
Requires-Python: >=3.13
Requires-Dist: numpy>=2.1.3
Requires-Dist: pydub>=0.25.1
Requires-Dist: numba>=0.61.0
Requires-Dist: audioop-lts>=0.2.1
Dynamic: author
Dynamic: classifier
Dynamic: description
Dynamic: description-content-type
Dynamic: home-page
Dynamic: requires-dist
Dynamic: requires-python
Dynamic: summary
